<?xml version="1.0"?>
<dataDocument xmlns:xsi="http://www.w3.org/2001/XMLSchema-instance" xsi:schemaLocation="example-7.xsd example-7.xsd">
    <engineType>
        <engineDetail>
            <metric>
                <emissions>Low-Emissions</emissions>
                <combustible>Gasoline</combustible>
                <combustible>Diesel</combustible>
                <combustible>Gasoline-Premium</combustible>
                <combustible>DieselB</combustible>
                <capacityUnit>Gallon</capacityUnit>
            </metric>
        </engineDetail>
    </engineType>
</dataDocument>